MANIFEST.in
README.txt
setup.py
docs/HISTORY.txt
docs/LICENSE.txt
src/silva/__init__.py
src/silva.app.mediacontent.egg-info/PKG-INFO
src/silva.app.mediacontent.egg-info/SOURCES.txt
src/silva.app.mediacontent.egg-info/dependency_links.txt
src/silva.app.mediacontent.egg-info/namespace_packages.txt
src/silva.app.mediacontent.egg-info/not-zip-safe
src/silva.app.mediacontent.egg-info/requires.txt
src/silva.app.mediacontent.egg-info/top_level.txt
src/silva/app/__init__.py
src/silva/app/mediacontent/__init__.py
src/silva/app/mediacontent/block.py
src/silva/app/mediacontent/configure.zcml
src/silva/app/mediacontent/content.py
src/silva/app/mediacontent/embed.png
src/silva/app/mediacontent/embed.py
src/silva/app/mediacontent/ftesting.zcml
src/silva/app/mediacontent/interfaces.py
src/silva/app/mediacontent/mediacontent.png
src/silva/app/mediacontent/slideshow.cpt
src/silva/app/mediacontent/testing.py
src/silva/app/mediacontent/content_templates/mediacontentview.cpt
src/silva/app/mediacontent/silvaxml/__init__.py
src/silva/app/mediacontent/silvaxml/xmlexport.py
src/silva/app/mediacontent/silvaxml/xmlimport.py
src/silva/app/mediacontent/static/slideshow.css
src/silva/app/mediacontent/static/slideshow.js
src/silva/app/mediacontent/static/slideshow.png
src/silva/app/mediacontent/tests/__init__.py
src/silva/app/mediacontent/tests/test_xml_export.py
src/silva/app/mediacontent/tests/test_xml_import.py
src/silva/app/mediacontent/tests/data/test_export_mediacontent.silvaxml
src/silva/app/mediacontent/tests/data/test_export_slideshow_block.silvaxml
src/silva/app/mediacontent/tests/data/test_import_slideshow_block.silvaxml