Metadata-Version: 1.1
Name: silva.app.mediacontent
Version: 3.0.2
Summary: Media content types for Silva CMS
Home-page: https://github.com/silvacms/silva.app.mediacontent
Author: Antonin Amand
Author-email: info@infrae.com
License: BSD
Keywords: media silva infrae
Platform: UNKNOWN
Classifier: Environment :: Web Environment
Classifier: Intended Audience :: Developers
Classifier: License :: OSI Approved :: Zope Public License
Classifier: Programming Language :: Python
Classifier: Topic :: Software Development :: Libraries :: Python Modules
Classifier: Framework :: Zope2
